
{
	"type": "FeatureCollection",
	"features": [{
		"type": "Feature",
		"properties": {
			"name": "左安浦园"
		},
		"geometry": {
			"type": "MultiPolygon",
			"coordinates": [
				[
					[
						[116.436996,39.874995],
                        [116.438935,39.874749],
                        [116.438954,39.874588],
                        [116.439585,39.87458],
                        [116.439466,39.872802],
                        [116.437033,39.872885]
					]
				]
			]
		}
	}
	]
}